helloworld/__init__.py
helloworld/cli.py
helloworld/helloworld.py
pyconuk_helloworld-0.1.0.dist-info/DESCRIPTION.rst
pyconuk_helloworld-0.1.0.dist-info/METADATA
pyconuk_helloworld-0.1.0.dist-info/RECORD
pyconuk_helloworld-0.1.0.dist-info/WHEEL
pyconuk_helloworld-0.1.0.dist-info/entry_points.txt
pyconuk_helloworld-0.1.0.dist-info/metadata.json
pyconuk_helloworld-0.1.0.dist-info/top_level.txt
