Metadata-Version: 2.0
Name: pyconuk-helloworld
Version: 0.1.0
Summary: A hello world package
Home-page: https://github.com/vitorbaptista/pyconuk_helloworld
Author: Vitor Baptista
Author-email: vitor@vitorbaptista.com
License: MIT
Platform: UNKNOWN
Classifier: Development Status :: 3 - Alpha
Classifier: License :: OSI Approved :: MIT License
Classifier: Operating System :: OS Independent
Classifier: Programming Language :: Python
Classifier: Programming Language :: Python :: 2
Classifier: Programming Language :: Python :: 2.7
Classifier: Programming Language :: Python :: 3
Classifier: Programming Language :: Python :: 3.3
Classifier: Programming Language :: Python :: 3.4
Classifier: Programming Language :: Python :: 3.5
